nmh/__init__.py
nmh/__main__.py
nmh/git/github.py
nmh/pathutils.py
nmh-0.1.0.dist-info/WHEEL
nmh-0.1.0.dist-info/METADATA
nmh-0.1.0.dist-info/RECORD
