Metadata-Version: 2.1
Name: nmh
Version: 0.1.0
Summary: 
Author: Huy tran
Author-email: huy.td183768@sis.hust.edu.vn
Requires-Python: >=3.9,<4.0
Classifier: Programming Language :: Python :: 3
Classifier: Programming Language :: Python :: 3.9
Requires-Dist: click (>=8.0.1,<9.0.0)
Requires-Dist: requests (>=2.26.0,<3.0.0)
